pyFAT_astro/FAT_Galaxy_Loop.py
pyFAT_astro/__init__.py
pyFAT_astro/main.py
pyFAT_astro/Installation_Check/ModelInput.def
pyFAT_astro/Installation_Check/NGC_2903.fits
pyFAT_astro/Installation_Check/__init__.py
pyFAT_astro/Support/__init__.py
pyFAT_astro/Support/clean_functions.py
pyFAT_astro/Support/constants.py
pyFAT_astro/Support/development_functions.py
pyFAT_astro/Support/fat_errors.py
pyFAT_astro/Support/fits_functions.py
pyFAT_astro/Support/log_functions.py
pyFAT_astro/Support/modify_template.py
pyFAT_astro/Support/read_functions.py
pyFAT_astro/Support/run_functions.py
pyFAT_astro/Support/support_functions.py
pyFAT_astro/Support/write_functions.py
pyFAT_astro/Templates/TRM_errors_FAT.yml
pyFAT_astro/Templates/__init__.py
pyFAT_astro/Templates/sofia_template.par
pyFAT_astro/Templates/template.def
pyFAT_astro/config/FAT_Input_Catalogue.txt
pyFAT_astro/config/__init__.py
pyFAT_astro/config/defaults.py
pyfat_astro-0.1.9.dist-info/METADATA
pyfat_astro-0.1.9.dist-info/WHEEL
pyfat_astro-0.1.9.dist-info/entry_points.txt
pyfat_astro-0.1.9.dist-info/licenses/LICENSE
pyfat_astro-0.1.9.dist-info/RECORD
