Metadata-Version: 2.4
Name: pyFAT_astro
Version: 0.1.9
Summary: Development Status :: 4 - Beta
Project-URL: Homepage, https://github.com/PeterKamphuis/pyFAT-astro
Author-email: "P. Kamphuis" <peterkamphuisastronomy@gmail.com>
License-Expression: GPL-3.0-or-later
License-File: LICENSE
Classifier: Development Status :: 4 - Beta
Classifier: Intended Audience :: Science/Research
Classifier: License :: OSI Approved :: GNU General Public License v3 (GPLv3)
Classifier: Operating System :: POSIX :: Linux
Classifier: Programming Language :: Python :: 3
Classifier: Topic :: Scientific/Engineering :: Astronomy
Requires-Python: >=3.8
Requires-Dist: astropy
Requires-Dist: future-fstrings
Requires-Dist: importlib-metadata
Requires-Dist: importlib-resources>=3.3.0
Requires-Dist: make-moments>=1.0.8
Requires-Dist: matplotlib
Requires-Dist: numpy>=1.14
Requires-Dist: omegaconf>=2.2.2
Requires-Dist: psutil
Requires-Dist: scipy
Requires-Dist: trm-errors>=0.1.0
